SConsider/Anything.py
SConsider/Callback.py
SConsider/KillableThread.py
SConsider/LibFinder.py
SConsider/Logging.py
SConsider/Main.py
SConsider/PackageRegistry.py
SConsider/PopenHelper.py
SConsider/ServerExtensions.py
SConsider/SomeUtils.py
SConsider/__init__.py
SConsider/_version.py
SConsider/deprecation.py
SConsider/dictconfig.py
SConsider/logging.yaml
SConsider/singleton.py
SConsider/3rdparty/boost/boost.src.sconsider
SConsider/3rdparty/boost/boost.sys.sconsider
SConsider/3rdparty/cute/cute.src.sconsider
SConsider/3rdparty/cute/cute.sys.sconsider
SConsider/3rdparty/iplanetLDAP/iplanetLDAP.bin.sconsider
SConsider/3rdparty/iplanetLDAP/iplanetLDAP.sys.sconsider
SConsider/3rdparty/loki/loki.src.sconsider
SConsider/3rdparty/loki/loki.sys.sconsider
SConsider/3rdparty/mqm/mqm.bin.sconsider
SConsider/3rdparty/mqm/mqm.sys.sconsider
SConsider/3rdparty/mysql/mysql.bin.sconsider
SConsider/3rdparty/mysql/mysql.sys.sconsider
SConsider/3rdparty/openssl/openssl.bin.sconsider
SConsider/3rdparty/openssl/openssl.sys.sconsider
SConsider/3rdparty/oracle/oracle.bin.sconsider
SConsider/3rdparty/oracle/oracle.sys.sconsider
SConsider/3rdparty/rsa/rsa.bin.sconsider
SConsider/3rdparty/rsa/rsa.sys.sconsider
SConsider/3rdparty/sybase/sybase.bin.sconsider
SConsider/3rdparty/sybase/sybase.sys.sconsider
SConsider/3rdparty/xms/xms.bin.sconsider
SConsider/3rdparty/xms/xms.sys.sconsider
SConsider/3rdparty/zlib/zlib.src.sconsider
SConsider/3rdparty/zlib/zlib.sys.sconsider
SConsider/maintenance/ChangeDLLNames.py
SConsider/maintenance/ChangeImportLines.py
SConsider/maintenance/WD2Coast.py
SConsider/maintenance/__init__.py
SConsider/site_tools/ConfigureHelper.py
SConsider/site_tools/DoxygenBuilder.py
SConsider/site_tools/EclipseDebugLaunchWriter.py
SConsider/site_tools/ExcludeDirectoryHelper.py
SConsider/site_tools/OutputDirectoryHelper.py
SConsider/site_tools/Package.py
SConsider/site_tools/RunBuilder.py
SConsider/site_tools/SubstInFileBuilder.py
SConsider/site_tools/SystemLibsInstallBuilder.py
SConsider-0.3.21.dist-info/LICENSE.txt
SConsider-0.3.21.dist-info/METADATA
SConsider-0.3.21.dist-info/WHEEL
SConsider-0.3.21.dist-info/top_level.txt
SConsider-0.3.21.dist-info/RECORD
