Metadata-Version: 2.1
Name: SConsider
Version: 0.3.21
Summary: scons build system extension
Home-page: https://gitlab.dev.ifs.hsr.ch/ifs/sconsider
Author: Marcel Huber
Author-email: marcel.huber@hsr.ch
License: BSD
Keywords: sconsider,scons,build
Platform: UNKNOWN
Classifier: Development Status :: 4 - Beta
Classifier: Environment :: Console
Classifier: Intended Audience :: Developers
Classifier: License :: OSI Approved :: BSD License
Classifier: Natural Language :: English
Classifier: Operating System :: MacOS :: MacOS X
Classifier: Operating System :: Microsoft :: Windows
Classifier: Operating System :: POSIX :: Linux
Classifier: Operating System :: POSIX :: SunOS/Solaris
Classifier: Programming Language :: Python
Classifier: Programming Language :: Python :: 2.6
Classifier: Programming Language :: Python :: 2.7
Classifier: Topic :: Software Development :: Build Tools
Requires-Dist: subprocess32
Requires-Dist: pyaml
Requires-Dist: pyopenssl
Requires-Dist: ordereddict
Requires-Dist: lepl
Requires-Dist: scons (~=2.5.0)
